optuna/__init__.py
optuna/_callbacks.py
optuna/_convert_positional_args.py
optuna/_deprecated.py
optuna/_experimental.py
optuna/_imports.py
optuna/_transform.py
optuna/_typing.py
optuna/cli.py
optuna/distributions.py
optuna/exceptions.py
optuna/logging.py
optuna/progress_bar.py
optuna/py.typed
optuna/version.py
optuna/_gp/__init__.py
optuna/_gp/acqf.py
optuna/_gp/gp.py
optuna/_gp/optim_mixed.py
optuna/_gp/optim_sample.py
optuna/_gp/prior.py
optuna/_gp/search_space.py
optuna/_hypervolume/__init__.py
optuna/_hypervolume/hssp.py
optuna/_hypervolume/wfg.py
optuna/artifacts/__init__.py
optuna/artifacts/_backoff.py
optuna/artifacts/_boto3.py
optuna/artifacts/_download.py
optuna/artifacts/_filesystem.py
optuna/artifacts/_gcs.py
optuna/artifacts/_list_artifact_meta.py
optuna/artifacts/_protocol.py
optuna/artifacts/_upload.py
optuna/artifacts/exceptions.py
optuna/importance/__init__.py
optuna/importance/_base.py
optuna/importance/_mean_decrease_impurity.py
optuna/importance/_fanova/__init__.py
optuna/importance/_fanova/_evaluator.py
optuna/importance/_fanova/_fanova.py
optuna/importance/_fanova/_tree.py
optuna/importance/_ped_anova/__init__.py
optuna/importance/_ped_anova/evaluator.py
optuna/importance/_ped_anova/scott_parzen_estimator.py
optuna/integration/__init__.py
optuna/integration/botorch.py
optuna/integration/catboost.py
optuna/integration/chainer.py
optuna/integration/chainermn.py
optuna/integration/cma.py
optuna/integration/dask.py
optuna/integration/fastaiv2.py
optuna/integration/keras.py
optuna/integration/lightgbm.py
optuna/integration/mlflow.py
optuna/integration/mxnet.py
optuna/integration/pytorch_distributed.py
optuna/integration/pytorch_ignite.py
optuna/integration/pytorch_lightning.py
optuna/integration/shap.py
optuna/integration/sklearn.py
optuna/integration/skorch.py
optuna/integration/tensorboard.py
optuna/integration/tensorflow.py
optuna/integration/tfkeras.py
optuna/integration/wandb.py
optuna/integration/xgboost.py
optuna-4.1.0.dist-info/LICENSE
optuna-4.1.0.dist-info/LICENSE_THIRD_PARTY
optuna-4.1.0.dist-info/METADATA
optuna-4.1.0.dist-info/WHEEL
optuna-4.1.0.dist-info/entry_points.txt
optuna-4.1.0.dist-info/top_level.txt
optuna-4.1.0.dist-info/RECORD
