Metadata-Version: 2.1
Name: optuna
Version: 4.1.0
Summary: A hyperparameter optimization framework
Author: Takuya Akiba
Project-URL: homepage, https://optuna.org/
Project-URL: repository, https://github.com/optuna/optuna
Project-URL: documentation, https://optuna.readthedocs.io
Project-URL: bugtracker, https://github.com/optuna/optuna/issues
Classifier: Development Status :: 5 - Production/Stable
Classifier: Intended Audience :: Science/Research
Classifier: Intended Audience :: Developers
Classifier: License :: OSI Approved :: MIT License
Classifier: Programming Language :: Python :: 3
Classifier: Programming Language :: Python :: 3.8
Classifier: Programming Language :: Python :: 3.9
Classifier: Programming Language :: Python :: 3.10
Classifier: Programming Language :: Python :: 3.11
Classifier: Programming Language :: Python :: 3.12
Classifier: Programming Language :: Python :: 3.13
Classifier: Programming Language :: Python :: 3 :: Only
Classifier: Topic :: Scientific/Engineering
Classifier: Topic :: Scientific/Engineering :: Mathematics
Classifier: Topic :: Scientific/Engineering :: Artificial Intelligence
Classifier: Topic :: Software Development
Classifier: Topic :: Software Development :: Libraries
Classifier: Topic :: Software Development :: Libraries :: Python Modules
Requires-Python: >=3.8
License-File: LICENSE
License-File: LICENSE_THIRD_PARTY
Requires-Dist: alembic>=1.5.0
Requires-Dist: colorlog
Requires-Dist: numpy
Requires-Dist: packaging>=20.0
Requires-Dist: sqlalchemy>=1.4.2
Requires-Dist: tqdm
Requires-Dist: PyYAML
Provides-Extra: benchmark
Requires-Dist: asv>=0.5.0; extra == "benchmark"
Requires-Dist: cma; extra == "benchmark"
Requires-Dist: virtualenv; extra == "benchmark"
Provides-Extra: checking
Requires-Dist: black; extra == "checking"
Requires-Dist: blackdoc; extra == "checking"
Requires-Dist: flake8; extra == "checking"
Requires-Dist: isort; extra == "checking"
Requires-Dist: mypy; extra == "checking"
Requires-Dist: mypy_boto3_s3; extra == "checking"
Requires-Dist: types-PyYAML; extra == "checking"
Requires-Dist: types-redis; extra == "checking"
Requires-Dist: types-setuptools; extra == "checking"
Requires-Dist: types-tqdm; extra == "checking"
Requires-Dist: typing_extensions>=3.10.0.0; extra == "checking"
Provides-Extra: document
Requires-Dist: ase; extra == "document"
Requires-Dist: cmaes>=0.10.0; extra == "document"
Requires-Dist: fvcore; extra == "document"
Requires-Dist: kaleido; extra == "document"
Requires-Dist: lightgbm; extra == "document"
Requires-Dist: matplotlib!=3.6.0; extra == "document"
Requires-Dist: pandas; extra == "document"
Requires-Dist: pillow; extra == "document"
Requires-Dist: plotly>=4.9.0; extra == "document"
Requires-Dist: scikit-learn; extra == "document"
Requires-Dist: sphinx; extra == "document"
Requires-Dist: sphinx-copybutton; extra == "document"
Requires-Dist: sphinx-gallery; extra == "document"
Requires-Dist: sphinx_rtd_theme>=1.2.0; extra == "document"
Requires-Dist: torch; extra == "document"
Requires-Dist: torchvision; extra == "document"
Provides-Extra: optional
Requires-Dist: boto3; extra == "optional"
Requires-Dist: cmaes>=0.10.0; extra == "optional"
Requires-Dist: google-cloud-storage; extra == "optional"
Requires-Dist: matplotlib!=3.6.0; extra == "optional"
Requires-Dist: pandas; extra == "optional"
Requires-Dist: plotly>=4.9.0; extra == "optional"
Requires-Dist: redis; extra == "optional"
Requires-Dist: scikit-learn>=0.24.2; extra == "optional"
Requires-Dist: scipy; extra == "optional"
Requires-Dist: torch; python_version <= "3.12" and extra == "optional"
Provides-Extra: test
Requires-Dist: coverage; extra == "test"
Requires-Dist: fakeredis[lua]; extra == "test"
Requires-Dist: kaleido; extra == "test"
Requires-Dist: moto; extra == "test"
Requires-Dist: pytest; extra == "test"
Requires-Dist: scipy>=1.9.2; extra == "test"
Requires-Dist: torch; python_version <= "3.12" and extra == "test"
